README.md
setup.py
StarburstPy.egg-info/PKG-INFO
StarburstPy.egg-info/SOURCES.txt
StarburstPy.egg-info/dependency_links.txt
StarburstPy.egg-info/top_level.txt
utils/__init__.py
utils/file_io.py
utils/sb_stdout.py