Metadata-Version: 2.1
Name: StarburstPy
Version: 0.9.1
Summary: Python Wrapper for Starburst99
Home-page: https://github.com/rjtanner/StarburstPy
Author: Ryan Tanner
Author-email: ryan.tanner@nasa.gov
License: UNKNOWN
Platform: UNKNOWN
Classifier: Programming Language :: Python :: 3
Classifier: License :: OSI Approved :: MIT License
Classifier: Operating System :: OS Independent
Requires-Python: >=3.6
